{
  "model_name": "PPA_PIPELINE",
  "model_version": "XGBoost_OptunaTPE_MonotonePrice",
  "features_version": "v1",
  "sklearn_version": "1.8.0",
  "numpy_version": "2.4.2",
  "cat_columns": [
    "product_sku_code",
    "customer",
    "top_brand",
    "flavor_internal",
    "pack_type_internal"
  ],
  "num_columns": [
    "promotion_indicator",
    "pack_size_internal",
    "units_per_package_internal",
    "price_per_litre"
  ],
  "price_per_litre": {
    "p1": 0.61245,
    "p99": 3.90167333317
  }
}